pysna/__init__.py
pysna/api.py
pysna/cli.py
pysna/fetch.py
pysna/process.py
pysna/utils.py
pysna-0.1.3.dist-info/LICENSE
pysna-0.1.3.dist-info/METADATA
pysna-0.1.3.dist-info/WHEEL
pysna-0.1.3.dist-info/entry_points.txt
pysna-0.1.3.dist-info/top_level.txt
pysna-0.1.3.dist-info/RECORD
