Metadata-Version: 2.1
Name: pysna
Version: 0.1.3
Summary: Python Package for Social Network Analytics
Home-page: https://github.com/mathun3003/PySNA
Author: Mathis Hunke
Author-email: mathun3003@gmail.com
License: MIT License
Project-URL: Documentation, https://mathun3003.github.io/PySNA/
Project-URL: Issue Tracker, https://github.com/mathun3003/PySNA/issues
Project-URL: Source Code, https://github.com/mathun3003/PySNA
Requires-Python: >=3.10
License-File: LICENSE
Requires-Dist: tweepy ~=4.12.1
Requires-Dist: argparse ~=1.4.0
Requires-Dist: numpy ~=1.24.0
Requires-Dist: python-dotenv ~=0.21.0
Requires-Dist: vaderSentiment ~=3.3.2
Requires-Dist: pandas ~=1.5.3
